[
	{
		"inputs": [
			{
				"internalType": "contract IERC20",
				"name": "_USX",
				"type": "address"
			},
			{
				"internalType": "contract IERC20",
				"name": "_HYDRO",
				"type": "address"
			},
			{
				"internalType": "uint256",
				"name": "_globalCollateralRatio",
				"type": "uint256"
			}
		],
		"stateMutability": "nonpayable",
		"type": "constructor"
	},
	{
		"anonymous": false,
		"inputs": [
			{
				"indexed": false,
				"internalType": "uint256",
				"name": "mint",
				"type": "uint256"
			},
			{
				"indexed": false,
				"internalType": "uint256",
				"name": "redeem",
				"type": "uint256"
			}
		],
		"name": "FeesChanged",
		"type": "event"
	},
	{
		"anonymous": false,
		"inputs": [
			{
				"indexed": true,
				"internalType": "address",
				"name": "previousOwner",
				"type": "address"
			},
			{
				"indexed": true,
				"internalType": "address",
				"name": "newOwner",
				"type": "address"
			}
		],
		"name": "OwnershipTransferred",
		"type": "event"
	},
	{
		"inputs": [],
		"name": "HYDRO",
		"outputs": [
			{
				"internalType": "contract IERC20",
				"name": "",
				"type": "address"
			}
		],
		"stateMutability": "view",
		"type": "function",
		"constant": true
	},
	{
		"inputs": [],
		"name": "USX",
		"outputs": [
			{
				"internalType": "contract IERC20",
				"name": "",
				"type": "address"
			}
		],
		"stateMutability": "view",
		"type": "function",
		"constant": true
	},
	{
		"inputs": [
			{
				"internalType": "address",
				"name": "",
				"type": "address"
			}
		],
		"name": "USXPools",
		"outputs": [
			{
				"internalType": "bool",
				"name": "",
				"type": "bool"
			}
		],
		"stateMutability": "view",
		"type": "function",
		"constant": true
	},
	{
		"inputs": [
			{
				"internalType": "uint256",
				"name": "",
				"type": "uint256"
			}
		],
		"name": "USXPoolsArray",
		"outputs": [
			{
				"internalType": "address",
				"name": "",
				"type": "address"
			}
		],
		"stateMutability": "view",
		"type": "function",
		"constant": true
	},
	{
		"inputs": [
			{
				"internalType": "address",
				"name": "",
				"type": "address"
			}
		],
		"name": "allowedToMintUSX",
		"outputs": [
			{
				"internalType": "bool",
				"name": "",
				"type": "bool"
			}
		],
		"stateMutability": "view",
		"type": "function",
		"constant": true
	},
	{
		"inputs": [],
		"name": "globalCollateralRatio",
		"outputs": [
			{
				"internalType": "uint256",
				"name": "",
				"type": "uint256"
			}
		],
		"stateMutability": "view",
		"type": "function",
		"constant": true
	},
	{
		"inputs": [],
		"name": "mintPaused",
		"outputs": [
			{
				"internalType": "bool",
				"name": "",
				"type": "bool"
			}
		],
		"stateMutability": "view",
		"type": "function",
		"constant": true
	},
	{
		"inputs": [],
		"name": "mintingFee",
		"outputs": [
			{
				"internalType": "uint256",
				"name": "",
				"type": "uint256"
			}
		],
		"stateMutability": "view",
		"type": "function",
		"constant": true
	},
	{
		"inputs": [],
		"name": "owner",
		"outputs": [
			{
				"internalType": "address",
				"name": "",
				"type": "address"
			}
		],
		"stateMutability": "view",
		"type": "function",
		"constant": true
	},
	{
		"inputs": [],
		"name": "redeemFee",
		"outputs": [
			{
				"internalType": "uint256",
				"name": "",
				"type": "uint256"
			}
		],
		"stateMutability": "view",
		"type": "function",
		"constant": true
	},
	{
		"inputs": [],
		"name": "redeemPaused",
		"outputs": [
			{
				"internalType": "bool",
				"name": "",
				"type": "bool"
			}
		],
		"stateMutability": "view",
		"type": "function",
		"constant": true
	},
	{
		"inputs": [],
		"name": "renounceOwnership",
		"outputs": [],
		"stateMutability": "nonpayable",
		"type": "function"
	},
	{
		"inputs": [
			{
				"internalType": "address",
				"name": "newOwner",
				"type": "address"
			}
		],
		"name": "transferOwnership",
		"outputs": [],
		"stateMutability": "nonpayable",
		"type": "function"
	},
	{
		"inputs": [
			{
				"internalType": "address",
				"name": "_minter",
				"type": "address"
			}
		],
		"name": "addUSXMinterNotPool",
		"outputs": [],
		"stateMutability": "nonpayable",
		"type": "function"
	},
	{
		"inputs": [
			{
				"internalType": "address",
				"name": "_minter",
				"type": "address"
			}
		],
		"name": "removeUSXMinterNotPool",
		"outputs": [],
		"stateMutability": "nonpayable",
		"type": "function"
	},
	{
		"inputs": [
			{
				"internalType": "address",
				"name": "poolAddress",
				"type": "address"
			}
		],
		"name": "addPool",
		"outputs": [],
		"stateMutability": "nonpayable",
		"type": "function"
	},
	{
		"inputs": [
			{
				"internalType": "address[]",
				"name": "poolAddress",
				"type": "address[]"
			}
		],
		"name": "addPools",
		"outputs": [],
		"stateMutability": "nonpayable",
		"type": "function"
	},
	{
		"inputs": [
			{
				"internalType": "address",
				"name": "poolAddress",
				"type": "address"
			}
		],
		"name": "removePool",
		"outputs": [],
		"stateMutability": "nonpayable",
		"type": "function"
	},
	{
		"inputs": [
			{
				"internalType": "uint256",
				"name": "_globalCollateralRatio",
				"type": "uint256"
			}
		],
		"name": "setGlobalCollateralRatio",
		"outputs": [],
		"stateMutability": "nonpayable",
		"type": "function"
	},
	{
		"inputs": [
			{
				"internalType": "uint256",
				"name": "_mintingFee",
				"type": "uint256"
			},
			{
				"internalType": "uint256",
				"name": "_redeemFee",
				"type": "uint256"
			}
		],
		"name": "setFeesParameters",
		"outputs": [],
		"stateMutability": "nonpayable",
		"type": "function"
	},
	{
		"inputs": [],
		"name": "toggleMinting",
		"outputs": [],
		"stateMutability": "nonpayable",
		"type": "function"
	},
	{
		"inputs": [],
		"name": "toggleRedeeming",
		"outputs": [],
		"stateMutability": "nonpayable",
		"type": "function"
	},
	{
		"inputs": [],
		"name": "isMintPaused",
		"outputs": [
			{
				"internalType": "bool",
				"name": "",
				"type": "bool"
			}
		],
		"stateMutability": "view",
		"type": "function",
		"constant": true
	},
	{
		"inputs": [],
		"name": "isRedeemPaused",
		"outputs": [
			{
				"internalType": "bool",
				"name": "",
				"type": "bool"
			}
		],
		"stateMutability": "view",
		"type": "function",
		"constant": true
	},
	{
		"inputs": [
			{
				"internalType": "address",
				"name": "pool",
				"type": "address"
			}
		],
		"name": "isPool",
		"outputs": [
			{
				"internalType": "bool",
				"name": "",
				"type": "bool"
			}
		],
		"stateMutability": "view",
		"type": "function",
		"constant": true
	},
	{
		"inputs": [
			{
				"internalType": "address",
				"name": "_minter",
				"type": "address"
			}
		],
		"name": "isAllowedToMint",
		"outputs": [
			{
				"internalType": "bool",
				"name": "",
				"type": "bool"
			}
		],
		"stateMutability": "view",
		"type": "function",
		"constant": true
	},
	{
		"inputs": [],
		"name": "getGlobalCollateralRatio",
		"outputs": [
			{
				"internalType": "uint256",
				"name": "",
				"type": "uint256"
			}
		],
		"stateMutability": "view",
		"type": "function",
		"constant": true
	},
	{
		"inputs": [],
		"name": "getGlobalCollateralValue",
		"outputs": [
			{
				"internalType": "uint256",
				"name": "",
				"type": "uint256"
			}
		],
		"stateMutability": "view",
		"type": "function",
		"constant": true
	},
	{
		"inputs": [],
		"name": "getUSXSupply",
		"outputs": [
			{
				"internalType": "uint256",
				"name": "",
				"type": "uint256"
			}
		],
		"stateMutability": "view",
		"type": "function",
		"constant": true
	},
	{
		"inputs": [],
		"name": "getMintingFee",
		"outputs": [
			{
				"internalType": "uint256",
				"name": "",
				"type": "uint256"
			}
		],
		"stateMutability": "view",
		"type": "function",
		"constant": true
	},
	{
		"inputs": [],
		"name": "getRedeemFee",
		"outputs": [
			{
				"internalType": "uint256",
				"name": "",
				"type": "uint256"
			}
		],
		"stateMutability": "view",
		"type": "function",
		"constant": true
	},
	{
		"inputs": [],
		"name": "getTargetCollateralValue",
		"outputs": [
			{
				"internalType": "uint256",
				"name": "",
				"type": "uint256"
			}
		],
		"stateMutability": "view",
		"type": "function",
		"constant": true
	},
	{
		"inputs": [],
		"name": "getPercentCollateralized",
		"outputs": [
			{
				"internalType": "uint256",
				"name": "",
				"type": "uint256"
			}
		],
		"stateMutability": "view",
		"type": "function",
		"constant": true
	},
	{
		"inputs": [],
		"name": "getUSXInfo",
		"outputs": [
			{
				"internalType": "uint256",
				"name": "",
				"type": "uint256"
			},
			{
				"internalType": "uint256",
				"name": "",
				"type": "uint256"
			},
			{
				"internalType": "uint256",
				"name": "",
				"type": "uint256"
			},
			{
				"internalType": "uint256",
				"name": "",
				"type": "uint256"
			},
			{
				"internalType": "uint256",
				"name": "",
				"type": "uint256"
			},
			{
				"internalType": "uint256",
				"name": "",
				"type": "uint256"
			}
		],
		"stateMutability": "view",
		"type": "function",
		"constant": true
	}
]
